Workbook

Sheet Costos_por_Ciudad
A1: ciudad | B1: Tecnico | C1: Tipo Vuelo | D1: gps_total | E1: gps_internos | F1: % Internos | G1: Puntos | H1: sueldo | I1: Almuerzos | J1: Alojamientos | K1: Viajes | L1: Traslado Interno | M1: Total Interno | N1: gps_externos | O1: pxq_unit_uf_gps | P1: pxq_uf | Q1: Total Externos | R1: flete_uf | S1: Materiales_uf | T1: TOTAL PROYECTO | U1: Extras 10% | V1: accesorios | W1: total_ciudad_uf
A2: Temuco | B2: Interno | C2: Terrestre Los ang- Tem | D2: =E2+N2 -> 14 | E2: 14 | F2: =E2/SUM($E$2:$E$16) -> 0.15217391 | G2: =31*570*E2/39500 -> 6.2627848 | H2: =580000*0.75*F2*3/39500 -> 5.0275179 | I2: =4*20000/39500 -> 2.0253165 | J2: =4*1.1 -> 4.4 | K2: =(164*0.03/10)+5755/39500 -> 0.6376962 | L2: =4*(5000/39500) -> 0.50632911 | M2: =SUM(L2+K2+J2+I2+H2+G2) -> 18.859644 | N2: 0 | O2: 2 | P2: =O2*N2 -> 0 | Q2: =P2 -> 0 | R2: 0 | S2: =0.2*D2 -> 2.8 | T2: =S2+Q2+M2 -> 21.659644 | U2: =T2*1.1 -> 23.825609 | V2: 28.14 | W2: 59.284304
A3: Talca | B3: Interno | C3: Terrestre Curi-Tal | D3: =E3+N3 -> 9 | E3: 9 | F3: =E3/SUM($E$2:$E$16) -> 0.097826087 | G3: =31*570*E3/39500 -> 4.0260759 | H3: =580000*0.75*F3*3/39500 -> 3.2319758 | I3: =2*20000/39500 -> 1.0126582 | J3: =2*1.1 -> 2.2 | K3: =(66*0.03/10)+2318/39500 -> 0.25668354 | L3: =2*(5000/39500) -> 0.25316456 | M3: =SUM(L3+K3+J3+I3+H3+G3) -> 10.980558 | N3: 0 | O3: 2 | P3: =O3*N3 -> 0 | Q3: =P3 -> 0 | R3: 0 | S3: =0.2*D3 -> 1.8 | T3: =S3+Q3+M3 -> 12.780558 | U3: =T3*1.1 -> 14.058614 | V3: 18.09 | W3: 38.24357
A4: Santiago | B4: Interno | C4: Base | D4: =E4+N4 -> 19 | E4: 19 | F4: =E4/SUM($E$2:$E$16) -> 0.20652174 | G4: =31*570*E4/39500 -> 8.4994937 | H4: =580000*0.75*F4*3/39500 -> 6.82306 | I4: =5*20000/39500 -> 2.5316456 | J4: 0 | K4: =((257*0.03/10)+13000/39500) -> 1.1001139 | L4: =5*(5000/39500) -> 0.63291139 | M4: =SUM(L4+K4+J4+I4+H4+G4) -> 19.587225 | N4: 0 | O4: 2 | P4: =O4*N4 -> 0 | Q4: =P4+R4 -> 0 | R4: 0 | S4: =0.2*D4 -> 3.8 | T4: =S4+Q4+M4 -> 23.387225 | U4: =T4*1.1 -> 25.725947 | V4: 38.19 | W4: 38.19
A5: Coquimbo | B5: Externo | D5: =E5+N5 -> 8 | E5: 0 | F5: =E5/SUM($E$2:$E$16) -> 0 | G5: =31*570*E5/39500 -> 0 | H5: =580000*0.75*F5*3/39500 -> 0 | I5: =IFERROR(VLOOKUP(A5,Hoja1!A:B,2,0)*(20000/39500),0) -> 0 | J5: =IFERROR(VLOOKUP(A5,Hoja1!A:B,2,0)*1.1,0) -> 0 | K5: 0 | L5: =IFERROR(VLOOKUP(A5,Hoja1!A:B,2,0)*(5000/39500),0) -> 0 | M5: =SUM(L5+K5+J5+I5+H5+G5) -> 0 | N5: 8 | O5: 1.5 | P5: =O5*N5 -> 12 | Q5: =P5+R5 -> 12.368152 | R5: 0.3681519 | S5: =0.2*D5 -> 1.6 | T5: =S5+Q5+M5 -> 13.968152 | U5: =T5*1.1 -> 15.364967 | V5: 16.08 | W5: 34.048152
A6: Antofagasta | B6: Interno | C6: Terrestre Calm-Antof | D6: =E6+N6 -> 13 | E6: 13 | F6: =E6/SUM($E$2:$E$16) -> 0.14130435 | G6: =31*570*E6/39500 -> 5.815443 | H6: =580000*0.75*F6*3/39500 -> 4.6684095 | I6: =4*20000/39500 -> 2.0253165 | J6: =4*1.1 -> 4.4 | K6: =(((216/10)*0.03)+0.2)*2 -> 1.696 | L6: =4*(5000/39500) -> 0.50632911 | M6: =SUM(L6+K6+J6+I6+H6+G6)+R6 -> 20.611498 | N6: 0 | O6: 2 | P6: =O6*N6 -> 0 | Q6: =P6 -> 0 | R6: 1.5 | S6: =0.2*D6 -> 2.6 | T6: =S6+Q6+M6 -> 23.211498 | U6: =T6*1.1 -> 25.532648 | V6: 26.13 | W6: 26.13
A7: Puerto Montt | B7: Interno | C7: Terrestre Temu-Puertom | D7: =E7+N7 -> 6 | E7: 6 | F7: =E7/SUM($E$2:$E$16) -> 0.065217391 | G7: =31*570*E7/39500 -> 2.6840506 | H7: =580000*0.75*F7*3/39500 -> 2.1546505 | I7: =2*20000/39500 -> 1.0126582 | J7: =2*1.1 -> 2.2 | K7: =(354*0.03/10)+12350/39500 -> 1.3746582 | L7: =2*(5000/39500) -> 0.25316456 | M7: =SUM(L7+K7+J7+I7+H7+G7) -> 9.6791822 | N7: 0 | O7: 2 | P7: =O7*N7 -> 0 | Q7: =P7+R7 -> 0 | R7: 0 | S7: =0.2*D7 -> 1.2 | T7: =S7+Q7+M7 -> 10.879182 | U7: =T7*1.1 -> 11.9671 | V7: 12.06 | W7: 25.677063
A8: La Serena | B8: Externo | D8: =E8+N8 -> 6 | E8: 0 | F8: =E8/SUM($E$2:$E$16) -> 0 | G8: =31*570*E8/39500 -> 0 | H8: =580000*0.75*F8*3/39500 -> 0 | I8: =IFERROR(VLOOKUP(A8,Hoja1!A:B,2,0)*(20000/39500),0) -> 0 | J8: =IFERROR(VLOOKUP(A8,Hoja1!A:B,2,0)*1.1,0) -> 0 | K8: 0 | L8: =IFERROR(VLOOKUP(A8,Hoja1!A:B,2,0)*(5000/39500),0) -> 0 | M8: =SUM(L8+K8+J8+I8+H8+G8) -> 0 | N8: 6 | O8: 1.5 | P8: =O8*N8 -> 9 | Q8: =P8+R8 -> 9.3681519 | R8: 0.3681519 | S8: =0.2*D8 -> 1.2 | T8: =S8+Q8+M8 -> 10.568152 | U8: =T8*1.1 -> 11.624967 | V8: 12.06 | W8: 25.628152
A9: Concepción | B9: Externo | D9: =E9+N9 -> 6 | E9: 0 | F9: =E9/SUM($E$2:$E$16) -> 0 | G9: =31*570*E9/39500 -> 0 | H9: =580000*0.75*F9*3/39500 -> 0 | I9: =IFERROR(VLOOKUP(A9,Hoja1!A:B,2,0)*(20000/39500),0) -> 0 | J9: =IFERROR(VLOOKUP(A9,Hoja1!A:B,2,0)*1.1,0) -> 0 | K9: 0 | L9: =IFERROR(VLOOKUP(A9,Hoja1!A:B,2,0)*(5000/39500),0) -> 0 | M9: =SUM(L9+K9+J9+I9+H9+G9) -> 0 | N9: 6 | O9: 2 | P9: =O9*N9 -> 12 | Q9: =P9+R9 -> 12.358987 | R9: 0.35898734 | S9: =0.2*D9 -> 1.2 | T9: =S9+Q9+M9 -> 13.558987 | U9: =T9*1.1 -> 14.914886 | V9: 12.06 | W9: 25.618987
A10: Chillán | B10: Interno | C10: Base | D10: =E10+N10 -> 12 | E10: 12 | F10: =E10/SUM($E$2:$E$16) -> 0.13043478 | G10: =31*570*E10/39500 -> 5.3681013 | H10: =580000*0.75*F10*3/39500 -> 4.309301 | I10: =3*20000/39500 -> 1.5189873 | J10: 0 | K10: =(631*0.03/10)+22096/39500 -> 2.4523924 | L10: =3*(5000/39500) -> 0.37974684 | M10: =SUM(L10+K10+J10+I10+H10+G10)+R10 -> 14.428529 | N10: 0 | O10: 2 | P10: =O10*N10 -> 0 | Q10: =P10 -> 0 | R10: 0.4 | S10: =0.2*D10 -> 2.4 | T10: =S10+Q10+M10 -> 16.828529 | U10: =T10*1.1 -> 18.511382 | V10: 24.12 | W10: 24.12
A11: Chiloé | B11: Externo | D11: =E11+N11 -> 5 | E11: 0 | F11: =E11/SUM($E$2:$E$16) -> 0 | G11: =31*570*E11/39500 -> 0 | H11: =580000*0.75*F11*3/39500 -> 0 | I11: =IFERROR(VLOOKUP(A11,Hoja1!A:B,2,0)*(20000/39500),0) -> 0 | J11: =IFERROR(VLOOKUP(A11,Hoja1!A:B,2,0)*1.1,0) -> 0 | K11: 0 | L11: =IFERROR(VLOOKUP(A11,Hoja1!A:B,2,0)*(5000/39500),0) -> 0 | M11: =SUM(L11+K11+J11+I11+H11+G11) -> 0 | N11: 5 | O11: 2 | P11: =O11*N11 -> 10 | Q11: =P11+R11 -> 10.417063 | R11: 0.41706329 | S11: =0.2*D11 -> 1 | T11: =S11+Q11+M11 -> 11.417063 | U11: =T11*1.1 -> 12.55877 | V11: 10.05 | W11: 21.467063
A12: Curicó | B12: Interno | C12: Terrestre scl- Curi | D12: =E12+N12 -> 5 | E12: 5 | F12: =E12/SUM($E$2:$E$16) -> 0.054347826 | G12: =31*570*E12/39500 -> 2.2367089 | H12: =580000*0.75*F12*3/39500 -> 1.7955421 | I12: =2*20000/39500 -> 1.0126582 | J12: =2*1.1 -> 2.2 | K12: =(195*0.03/10)+10081/39500 -> 0.84021519 | L12: =2*(5000/39500) -> 0.25316456 | M12: =SUM(L12+K12+J12+I12+H12+G12)+R12 -> 8.3382889 | N12: 0 | O12: 2 | P12: =O12*N12 -> 0 | Q12: =P12 -> 0 | R12: 0 | S12: =0.2*D12 -> 1 | T12: =S12+Q12+M12 -> 9.3382889 | U12: =T12*1.1 -> 10.272118 | V12: 10.05 | W12: 21.40357
A13: Rancagua | B13: Interno | C13: Terrestre scl-ranc | D13: =E13+N13 -> 5 | E13: 5 | F13: =E13/SUM($E$2:$E$16) -> 0.054347826 | G13: =31*570*E13/39500 -> 2.2367089 | H13: =580000*0.75*F13*3/39500 -> 1.7955421 | I13: =2*20000/39500 -> 1.0126582 | J13: =2*1.1 -> 2.2 | K13: =(89*0.03/10)+7104/39500 -> 0.4468481 | L13: =2*(5000/39500) -> 0.25316456 | M13: =SUM(L13+K13+J13+I13+H13+G13) -> 7.9449218 | N13: 0 | O13: 2 | P13: =O13*N13 -> 0 | Q13: =P13 -> 0 | R13: 0 | S13: =0.2*D13 -> 1 | T13: =S13+Q13+M13 -> 8.9449218 | U13: =T13*1.1 -> 9.839414 | V13: 10.05 | W13: 21.39681
A14: Valparaíso | B14: Interno | C14: Terreste scl-valp | D14: =E14+N14 -> 5 | E14: 5 | F14: =E14/SUM($E$2:$E$16) -> 0.054347826 | G14: =31*570*E14/39500 -> 2.2367089 | H14: =580000*0.75*F14*3/39500 -> 1.7955421 | I14: =2*20000/39500 -> 1.0126582 | J14: =2*1.1 -> 2.2 | K14: =+(120*0.03/10)+8210/39500 -> 0.5678481 | L14: =2*(5000/39500) -> 0.25316456 | M14: =SUM(L14+K14+J14+I14+H14+G14) -> 8.0659218 | N14: 0 | O14: 2 | P14: =O14*N14 -> 0 | Q14: =P14 -> 0 | R14: 0 | S14: =0.2*D14 -> 1 | T14: =S14+Q14+M14 -> 9.0659218 | U14: =T14*1.1 -> 9.972514 | V14: 10.05 | W14: 21.39681
A15: Los Ángeles | B15: Interno | C15: Terrestre Chill-Los ang | D15: =E15+N15 -> 4 | E15: 4 | F15: =E15/SUM($E$2:$E$16) -> 0.043478261 | G15: =31*570*E15/39500 -> 1.7893671 | H15: =580000*0.75*F15*3/39500 -> 1.4364337 | I15: =1*20000/39500 -> 0.50632911 | J15: =1*1.1 -> 1.1 | K15: =(113*0.03/10)+3986/39500 -> 0.43991139 | L15: =1*(5000/39500) -> 0.12658228 | M15: =SUM(L15+K15+J15+I15+H15+G15) -> 5.3986236 | N15: 0 | O15: 2 | P15: =O15*N15 -> 0 | Q15: =P15+R15 -> 0 | R15: 0 | S15: =0.2*D15 -> 0.8 | T15: =S15+Q15+M15 -> 6.1986236 | U15: =T15*1.1 -> 6.8184859 | V15: 8.04 | W15: 17.198987
A16: Curanilahue | B16: Externo | D16: =E16+N16 -> 4 | E16: 0 | F16: =E16/SUM($E$2:$E$16) -> 0 | G16: =31*570*E16/39500 -> 0 | H16: =580000*0.75*F16*3/39500 -> 0 | I16: =IFERROR(VLOOKUP(A16,Hoja1!A:B,2,0)*(20000/39500),0) -> 0 | J16: =IFERROR(VLOOKUP(A16,Hoja1!A:B,2,0)*1.1,0) -> 0 | K16: 0 | L16: =IFERROR(VLOOKUP(A16,Hoja1!A:B,2,0)*(5000/39500),0) -> 0 | M16: =SUM(L16+K16+J16+I16+H16+G16) -> 0 | N16: 4 | O16: 2 | P16: =O16*N16 -> 8 | Q16: =P16+R16 -> 8.3589873 | R16: 0.35898734 | S16: =0.2*D16 -> 0.8 | T16: =S16+Q16+M16 -> 9.1589873 | U16: =T16*1.1 -> 10.074886 | V16: 8.04 | W16: 17.198987
C21: Evaluacion Rabie | D21: 2026 | E21: 2027 | F21: 2028
I22: Total Gps Interno | J22: 92
C23: Servicio GPS | D23: =0.6*$J$24*11 -> 798.6 | E23: =0.6*$J$24*12 -> 871.2 | F23: =0.6*$J$24*12 -> 871.2 | I23: Total Gps Externo | J23: 29
C24: Instalaciones | D24: =1.5*SUM(D5:D16,D2:D3)+1*D4 -> 172 | E24: - | F24: - | I24: Total | J24: =J23+J22 -> 121
C25: Ingresos | D25: =SUM(D23:D24) -> 970.6 | E25: =SUM(E23:E24) -> 871.2 | F25: =SUM(F23:F24) -> 871.2
C27: Puntos | D27: =-SUM(G2:G16) -> -41.155443 | E27: - | F27: -
C28: Sueldo | D28: =-SUM(H2:H16) -> -33.037975 | E28: - | F28: - | I28: Ciudades Internos | J28: 10
C29: Almuerzos | D29: =-SUM(I2:I16) -> -13.670886 | E29: - | F29: - | I29: Ciudades Externos | J29: 5
C30: Alojamientos | D30: =-SUM(J2:J16) -> -20.9 | E30: - | F30: -
C31: Materiales | D31: =-SUM(S2:S16) -> -24.2
C32: Viaje | D32: =-SUM(K2:K16) -> -9.8123671 | E32: - | F32: - | I32: UF/Kits | J32: =SUM(U2:U16)/J24 -> 1.8269612
C33: Traslado Int. | D33: =-SUM(L2:L16) -> -3.4177215 | E33: - | F33: -
C34: Total Flete | D34: =-SUM(R2:R16) -> -3.7713418 | E34: - | F34: -
C35: Externos | D35: =-SUM(P2:P16) -> -51 | E35: - | F35: -
C36: Sim | D36: =-(1000/39500)*$J$24*11 -> -33.696203 | E36: =-(1000/39500)*$J$24*12 -> -36.759494 | F36: =-(1000/39500)*$J$24*12 -> -36.759494
C37: Data Center | D37: =-0.014*$J$24*11 -> -18.634 | E37: =-0.014*$J$24*12 -> -20.328 | F37: =-0.014*$J$24*12 -> -20.328
C38: Kam 10% | D38: =-1000000*0.1*11/39500 -> -27.848101 | E38: =-1000000*0.1*12/39500 -> -30.379747 | F38: =-1000000*0.1*12/39500 -> -30.379747
C39: Egresos | D39: =SUM(D27:D38) -> -281.14404 | E39: =SUM(E27:E38) -> -87.467241 | F39: =SUM(F27:F38) -> -87.467241
C42: Inversion | D42: =-SUM(V2:V16) -> -243.21
C44: Total Año | D44: =D25+D39+D42 -> 446.24596 | E44: =E25+E39+E42 -> 783.73276 | F44: =F25+F39+F42 -> 783.73276
C45: Total Acumulado | D45: =D44 -> 446.24596 | E45: =D45+E44 -> 1229.9787 | F45: =E45+F44 -> 2013.7115
C46: Van 8% UF | D46: =NPV(8%,D45:F45) -> 3066.2483
C47: Van 8% CLP | D47: =D46*39500 -> 1.2111681e+08

Sheet Hoja1
A3: Etiquetas de fila | B3: Cuenta de dia
A4: Antofagasta | B4: 5
A5: Chillán | B5: 4
A6: Santiago | B6: 7
A7: Total general | B7: 16

Sheet Ruta
A2: Luis | B2: Santiago | C2: Valparaiso | D2: Rancagua | E2: Curico | F2: Talca
A3: Jimmy | B3: Chillan | C3: Los Angeles | D3: Temuco | E3: Puerto Montt
A4: Orlando | B4: Antofagasta

Sheet Plan_Diario
A1: tecnico | B1: dia | C1: ciudad_trabajo | D1: horas_instal | E1: gps_inst | F1: viaje_modo_manana | G1: viaje_h_manana | H1: duerme_en | I1: nota
A2: Jimmy | B2: 1 | C2: Chillán | D2: 4.5 | E2: 3 | F2: terrestre | G2: 0 | H2: Chillán
A3: Jimmy | B3: 2 | C3: Chillán | D3: 4.5 | E3: 3 | G3: 0 | H3: Chillán
A4: Jimmy | B4: 3 | C4: Chillán | D4: 4.5 | E4: 3 | G4: 0 | H4: Chillán
A5: Jimmy | B5: 4 | C5: Chillán | D5: 4.5 | E5: 3 | G5: 0 | H5: Chillán
A6: Luis | B6: 1 | C6: Santiago | D6: 4.5 | E6: 3 | F6: terrestre | G6: 0 | H6: Santiago
A7: Luis | B7: 2 | C7: Santiago | D7: 4.5 | E7: 3 | G7: 0 | H7: Santiago
A8: Luis | B8: 3 | C8: Santiago | D8: 4.5 | E8: 3 | G8: 0 | H8: Santiago
A9: Luis | B9: 4 | C9: Santiago | D9: 4.5 | E9: 3 | G9: 0 | H9: Santiago
A10: Luis | B10: 5 | C10: Santiago | D10: 4.5 | E10: 3 | G10: 0 | H10: Santiago
A11: Luis | B11: 6 | C11: Santiago | D11: 4.5 | E11: 3 | G11: 0 | H11: Santiago
A12: Luis | B12: 7 | C12: Santiago | D12: 1.5 | E12: 1 | G12: 0 | H12: Santiago
A13: Orlando | B13: 1 | C13: Antofagasta | D13: 4.5 | E13: 3 | F13: terrestre | G13: 0 | H13: Antofagasta
A14: Orlando | B14: 2 | C14: Antofagasta | D14: 4.5 | E14: 3 | G14: 0 | H14: Antofagasta
A15: Orlando | B15: 3 | C15: Antofagasta | D15: 4.5 | E15: 3 | G15: 0 | H15: Antofagasta
A16: Orlando | B16: 4 | C16: Antofagasta | D16: 4.5 | E16: 3 | G16: 0 | H16: Antofagasta
A17: Orlando | B17: 5 | C17: Antofagasta | D17: 1.5 | E17: 1 | G17: 0 | H17: Antofagasta
